{
    "arcgis": {
        "repository": {
            "local_archives": "C:\\Software\\Archives",
            "shared": false,
            "server": {
                "username": "changeit",
                "password": "changeit"
            },
            "files": {
                "ArcGIS_Mission_Server_Windows_110_182935.exe": {
                    "subfolder": "software/arcgis/11.0"
                }
            }
        }
    },
    "run_list": [
        "recipe[arcgis-repository::fileserver]",
        "recipe[arcgis-repository::files]"
    ]
}
