{
    "arcgis": {
        "repository": {
            "local_archives": "C:\\Software\\Archives",
            "shared": false,
            "server": {
            },
            "files": {
                "VC_redist.x64.exe": {
                    "url": "https://download.visualstudio.microsoft.com/download/pr/11100230/15ccb3f02745c7b206ad10373cbca89b/VC_redist.x64.exe"
                },
                "msodbcsql13.msi": {
                    "url": "https://download.microsoft.com/download/D/5/E/D5EEF288-A277-45C8-855B-8E2CB7E25B96/x64/msodbcsql.msi"
                },
                "msodbcsql17.msi": {
                    "url": "https://download.microsoft.com/download/E/6/B/E6BFDC7A-5BCD-4C51-9912-635646DA801E/en-US/17.5.2.1/x64/msodbcsql.msi"
                },
                "MsSqlCmdLnUtils.msi": {
                    "url": "https://download.microsoft.com/download/4/C/C/4CC1A229-3C56-4A7F-A3BA-F903C73E5895/EN/x64/MsSqlCmdLnUtils.msi"
                }
            }
        }
    },
    "run_list": [
        "recipe[arcgis-repository::fileserver]",
        "recipe[arcgis-repository::files]"
    ]
}
